gemgroq/__init__.py
gemgroq/api.py
gemgroq/cli.py
gemgroq/config.py
gemgroq-0.1.2.dist-info/LICENSE
gemgroq-0.1.2.dist-info/METADATA
gemgroq-0.1.2.dist-info/WHEEL
gemgroq-0.1.2.dist-info/entry_points.txt
gemgroq-0.1.2.dist-info/top_level.txt
gemgroq-0.1.2.dist-info/RECORD
