Metadata-Version: 2.1
Name: gemgroq
Version: 0.1.2
Summary: A unified API interface for Groq and Google's Gemini AI models
Home-page: https://github.com/yourusername/gemgroq
Author: Nassim Khatib
Author-email: your.email@example.com
Classifier: Development Status :: 3 - Alpha
Classifier: Intended Audience :: Developers
Classifier: License :: OSI Approved :: MIT License
Classifier: Operating System :: OS Independent
Classifier: Programming Language :: Python :: 3
Classifier: Programming Language :: Python :: 3.8
Classifier: Programming Language :: Python :: 3.9
Classifier: Programming Language :: Python :: 3.10
Classifier: Programming Language :: Python :: 3.11
Requires-Python: >=3.8
License-File: LICENSE
Requires-Dist: groq>=0.3.2
Requires-Dist: google-generativeai>=0.3.2
Requires-Dist: python-dotenv>=1.0.0
